[{"name": "Tom", "score": 580, "nivel": 4, "fecha": "2025-01-23 19:55"}, {"name": "asdf", "score": 580, "nivel": 4, "fecha": "2025-01-24 18:19"}, {"name": "Tom", "score": 580, "nivel": 4, "fecha": "2025-01-24 18:21"}, {"name": "Tom", "score": 580, "nivel": 4, "fecha": "2025-01-24 18:22"}, {"name": "jasd", "score": 580, "nivel": 4, "fecha": "2025-01-24 18:24"}, {"name": "T", "score": 580, "nivel": 4, "fecha": "2025-01-24 18:25"}, {"name": "f", "score": 540, "nivel": 4, "fecha": "2025-01-23 21:08"}, {"name": "Tom", "score": 510, "nivel": 3, "fecha": "2025-01-22 14:25"}, {"name": "Tom", "score": 510, "nivel": 3, "fecha": "2025-01-24 09:48"}, {"name": "Tom", "score": 510, "nivel": 3, "fecha": "2025-01-24 10:27"}]